sorda/__init__.py
sorda/configurable.py
sorda/sorda.py
sorda-0.1.dist-info/METADATA
sorda-0.1.dist-info/WHEEL
sorda-0.1.dist-info/top_level.txt
sorda-0.1.dist-info/RECORD
