Metadata-Version: 2.1
Name: sorda
Version: 0.1
Summary: Run excute
Home-page: https://github.com/Qinka/sorda
Author: qinka
Author-email: me@qinka.pro
License: UNKNOWN
Platform: UNKNOWN
